{ "indexes" : [ { "v" : 1, "key" : { "_id" : 1 }, "ns" : "rnc_production.msgs", "name" : "_id_" }, { "v" : 1, "key" : { "author" : 1 }, "ns" : "rnc_production.msgs", "name" : "author_1", "background" : true, "safe" : null }, { "v" : 1, "key" : { "created_dt" : 1 }, "ns" : "rnc_production.msgs", "name" : "created_dt_1", "background" : true, "safe" : null }, { "v" : 1, "key" : { "thread_id" : 1 }, "ns" : "rnc_production.msgs", "name" : "thread_id_1", "background" : true, "safe" : null }, { "v" : 1, "key" : { "title" : 1 }, "ns" : "rnc_production.msgs", "name" : "title_1", "background" : true, "safe" : null }, { "v" : 1, "key" : { "content" : 1 }, "ns" : "rnc_production.msgs", "name" : "content_1", "background" : true, "safe" : null } ] }